{
    "configurations": [
        {
            "name": "Linux",
            "includePath": [
                "${workspaceFolder}/**",
                "${vcpkgRoot}/arm64-linux/include",
                "/ssd/ros2_humble/src/ros2/rclcpp/rclcpp/include/**",
                "/ssd/ros2_humble/src/ros2/rclcpp/rclcpp/include/"
            ],
            "defines": [],
            "compilerPath": "/usr/bin/clang-10",
            "cStandard": "c17",
            "cppStandard": "c++14",
            "intelliSenseMode": "linux-clang-arm64"
        }
    ],
    "version": 4
}